e_drive/__init__.py
e_drive/__main__.py
e_drive/cards.py
e_drive/crc.py
e_drive/drone.py
e_drive/protocol.py
e_drive/receiver.py
e_drive/storage.py
e_drive/system.py
e_drive/update.py
e_drive/gui/__init__.py
e_drive/gui/card.py
e_drive/gui/cards.py
e_drive/gui/update.py
e_drive/tools/__init__.py
e_drive/tools/parser.py
e_drive/tools/update.py
e_drive-0.0.66.dist-info/LICENSE
e_drive-0.0.66.dist-info/METADATA
e_drive-0.0.66.dist-info/WHEEL
e_drive-0.0.66.dist-info/top_level.txt
e_drive-0.0.66.dist-info/RECORD
