Metadata-Version: 2.1
Name: e-drive
Version: 0.0.66
Summary: Library for E-DRIVE
Home-page: http://www.byrobot.co.kr
Author: BYROBOT
Author-email: dev@byrobot.co.kr
License: UNKNOWN
Platform: UNKNOWN
Requires-Dist: pyserial (>=3.4)
Requires-Dist: numpy (>=1.15.4)
Requires-Dist: colorama (>=0.4.0)
Requires-Dist: kivy (>=1.10.1)
